MANIFEST.in
NEWS.txt
README.rst
TODO.rst
setup.py
src/citeulike_api/__init__.py
src/citeulike_api/citeulike_api.py
src/citeulike_api/test_bibtex_output.py
src/citeulike_api/test_citeulikeapi.py
src/citeulike_api/util.py
src/citeulike_api.egg-info/PKG-INFO
src/citeulike_api.egg-info/SOURCES.txt
src/citeulike_api.egg-info/dependency_links.txt
src/citeulike_api.egg-info/not-zip-safe
src/citeulike_api.egg-info/requires.txt
src/citeulike_api.egg-info/top_level.txt
src/citeulike_api/output/__init__.py
src/citeulike_api/output/base.py
src/citeulike_api/output/bibtex.py
src/citeulike_api/output/rst.py