Metadata-Version: 1.0
Name: citeulike-api
Version: 0.1.1dev
Summary: a python api for http://citeulike.org/
Home-page: https://bitbucket.org/howthebodyworks/citeulike_api/src
Author: Dan MacKinlay
Author-email: pypi@email.possumpalace.org
License: BSD
Platform: UNKNOWN
Classifier: Development Status :: 3 - Alpha
Classifier: Intended Audience :: Science/Research
Classifier: License :: OSI Approved :: BSD License
Classifier: Programming Language :: Python :: 2.6
Classifier: Programming Language :: Python :: 2.7
Classifier: Topic :: Internet :: WWW/HTTP :: Browsers
